flask_debugtoolbar_warnings/__init__.py
flask_debugtoolbar_warnings/panel.py
flask_debugtoolbar_warnings/warnings_manager.py
flask_debugtoolbar_warnings/templates/warnings-panel.html
flask_debugtoolbar_warnings-0.1.0.dist-info/METADATA
flask_debugtoolbar_warnings-0.1.0.dist-info/RECORD
flask_debugtoolbar_warnings-0.1.0.dist-info/WHEEL
flask_debugtoolbar_warnings-0.1.0.dist-info/top_level.txt
