Metadata-Version: 2.1
Name: flask-debugtoolbar-warnings
Version: 0.1.0
Summary: Adds warnings support to Flask-Debugtoolbar
Home-page: https://github.com/flaskbb/flask-debugtoolbar-warnings
Author: Alec Nikolas Reiter
Author-email: alecreiter@gmail.com
License: MIT
Keywords: flask,debug,warnings
Platform: UNKNOWN
Classifier: Development Status :: 1 - Planning
Classifier: Framework :: Flask
Classifier: Environment :: Web Environment
Classifier: Intended Audience :: Developers
Classifier: License :: OSI Approved :: MIT License
Classifier: Programming Language :: Python :: 2.7
Classifier: Programming Language :: Python :: 3.4
Classifier: Programming Language :: Python :: 3.5
Classifier: Programming Language :: Python :: 3.6
Requires-Python: >=2.7,!=3.0.*,!=3.1.*,!=3.2.*,!=3.3.*
Requires-Dist: Flask (>=0.12.0)
Requires-Dist: flask-debugtoolbar (>=0.10.0)
